torii/__init__.py
torii/exception.py
torii/generate_doc.py
torii/generate_pythonApi_doc.py
torii/session.py
torii/torii_main.py
torii/dao/__init__.py
torii/dao/abstract_dao.py
torii/dao/business_object_dao.py
torii/data/__init__.py
torii/data/application.py
torii/data/business_object.py
torii/data/cluster.py
torii/data/picom.py
torii/data/record.py
torii/data/struct.py
torii/data/task.py
torii/data/torii_object.py
torii/decorators/__init__.py
torii/decorators/route_registry.py
torii/managers/__init__.py
torii/managers/dao_manager.py
torii/managers/user_manager.py
torii/services/__init__.py
torii/services/addon_service.py
torii/services/ai_service.py
torii/services/application_service.py
torii/services/bo_service.py
torii/services/bs_service.py
torii/services/file_service.py
torii/services/graph_service.py
torii/services/organisation_service.py
torii/services/picom_service.py
torii/services/profile_service.py
torii/services/service.py
torii/services/session_service.py
torii/services/task_service.py
torii/services/torii_service.py
fse.torii-1.0.43.dist-info/METADATA
fse.torii-1.0.43.dist-info/WHEEL
fse.torii-1.0.43.dist-info/top_level.txt
fse.torii-1.0.43.dist-info/RECORD
