Metadata-Version: 2.1
Name: fse.torii
Version: 1.0.43
Summary: Torii
Author: Fujitsu Systems Europe
Requires-Dist: requests-toolbelt ==1.0.0
Requires-Dist: numpy ==1.24.2
Requires-Dist: pymongo ==4.3.3
